<?xml version="1.0" standalone="yes"?>

<!-- See: http://utilitymill.com/utility/Regex_For_Range -->

<ControllerMetadata xmlns="metadata.xmlbeans.model.fc.lmn.org">

    <!-- The Controller Notes -->
    <Metadata>
        <Key>Controller.Notes</Key>
        <Value>Controller Notes</Value>
        <Regex>([a-zA-Z0-9'.,/ \-])*</Regex>
        <DataTypeName>String</DataTypeName>
        <Units>Dimensionless</Units>
        <Description>The Starinet VlfReceiver Controller Notes, for testing</Description>
    </Metadata>

</ControllerMetadata>

